{
	"Names": [	
		{"Name": "Afghanistan"},
		{"Name": "Aland Islands"},
		{"Name": "Albania"}, 
		{"Name": "Algeria"},
		{"Name": "American Samoa"}, 
		{"Name": "Andorra"},
		{"Name": "Angola"},
		{"Name": "Anguilla"}, 
		{"Name": "Antarctica"}, 
		{"Name": "Antigua Barbuda"}, 
		{"Name": "Argentina"},
		{"Name": "Armenia"}, 
		{"Name": "Aruba"}, 
		{"Name": "Australia"}, 
		{"Name": "Austria"},
		{"Name": "Azerbaijan"}, 
		{"Name": "Bahamas"}, 
		{"Name": "Bahrain"},
		{"Name": "Bangladesh"}, 
		{"Name": "Barbados"}, 
		{"Name": "Belarus"},
		{"Name": "Belgium"}, 
		{"Name": "Belize"},
		{"Name": "Benin"}, 
		{"Name": "Bermuda"},
		{"Name": "Bhutan"}, 
		{"Name": "Bolivia"}, 
		{"Name": "Bosnia Herzegovina"}, 
		{"Name": "Botswana"}, 
		{"Name": "Bouvet Island"},
		{"Name": "Brazil"},
		{"Name": "British Indian Territory"}, 
		{"Name": "Brunei Darussalam"},
		{"Name": "Bulgaria"},
		{"Name": "Burkina Faso"}, 
		{"Name": "Burundi"}, 
		{"Name": "Cambodia"}, 
		{"Name": "Cameroon"},
		{"Name": "Canada"}, 
		{"Name": "Cape Verde"},
		{"Name": "Cayman Islands"}, 
		{"Name": "Central African Republic"},
		{"Name": "Chad"}, 
		{"Name": "Chile"}, 
		{"Name": "China"}, 
		{"Name": "Christmas Island"}, 
		{"Name": "Cocos Islands"},
		{"Name": "Colombia"}, 
		{"Name": "Comoros"}, 
		{"Name": "Congo"},
		{"Name": "The Congo"},
		{"Name": "Cook Islands"},
		{"Name": "Costa Rica"}, 
		{"Name": "Cote Divoire"}, 
		{"Name": "Croatia"}, 
		{"Name": "Cuba"}, 
		{"Name": "Cyprus"}, 
		{"Name": "Czech Republic"}, 
		{"Name": "Denmark"},
		{"Name": "Djibouti"}, 
		{"Name": "Dominica"},
		{"Name": "Dominican Republic"}, 
		{"Name": "Ecuador"}, 
		{"Name": "Egypt"}, 
		{"Name": "El Salvador"},
		{"Name": "Equatorial Guinea"}, 
		{"Name": "Eritrea"}, 
		{"Name": "Estonia"}, 
		{"Name": "Ethiopia"},
		{"Name": "Falkland Island"},
		{"Name": "Faroe Islands"},
		{"Name": "Fiji"}, 
		{"Name": "Finland"},
		{"Name": "France"}, 
		{"Name": "French Guiana"},
		{"Name": "French Polynesia"}, 
		{"Name": "French Southern Territories"},
		{"Name": "Gabon"},
		{"Name": "Gambia"},
		{"Name": "Georgia"},
		{"Name": "Germany"},
		{"Name": "Ghana"},
		{"Name": "Gibraltar"},
		{"Name": "Greece"},
		{"Name": "Greenland"},
		{"Name": "Grenada"},
		{"Name": "Guadeloupe"},
		{"Name": "Guam"},
		{"Name": "Guatemala"},
		{"Name": "Guernsey"},
		{"Name": "Guinea"},
		{"Name": "Guinea-Bissau"},
		{"Name": "Guyana"},
		{"Name": "Haiti"},
		{"Name": "Heard Mcdonald Islands"},
		{"Name": "Holy See"},
		{"Name": "Honduras"},
		{"Name": "Hong Kong"},
		{"Name": "Hungary"},
		{"Name": "Iceland"},
		{"Name": "India"},
		{"Name": "Indonesia"},
		{"Name": "Iran"},
		{"Name": "Iraq"},
		{"Name": "Ireland"},
		{"Name": "Isle of Man"},
		{"Name": "Israel"},
		{"Name": "Italy"},
		{"Name": "Jamaica"},
		{"Name": "Japan"},
		{"Name": "Jersey"},
		{"Name": "Jordan"},
		{"Name": "Kazakhstan"},
		{"Name": "Kenya"},
		{"Name": "Kiribati"},
		{"Name": "Koreanorth"},
		{"Name": "Koreasouth"},
		{"Name": "Kuwait"},
		{"Name": "Kyrgyzstan"},
		{"Name": "Laos"},
		{"Name": "Latvia"},
		{"Name": "Lebanon"},
		{"Name": "Lesotho"},
		{"Name": "Liberia"},
		{"Name": "Libyan Arab Jamahiriya"},
		{"Name": "Liechtenstein"},
		{"Name": "Lithuania"},
		{"Name": "Luxembourg"},
		{"Name": "Macao"},
		{"Name": "Macedonia"},
		{"Name": "Madagascar"},
		{"Name": "Malawi"},
		{"Name": "Malaysia"},
		{"Name": "Maldives"},
		{"Name": "Mali"},
		{"Name": "Malta"},
		{"Name": "Marshall Islands"},
		{"Name": "Martinique"},
		{"Name": "Mauritania"},
		{"Name": "Mauritius"},
		{"Name": "Mayotte"},
		{"Name": "Mexico"},
		{"Name": "Micronesia Federated States"},
		{"Name": "Moldova Republic"},
		{"Name": "Monaco"},
		{"Name": "Mongolia"},
		{"Name": "Montserrat"},
		{"Name": "Morocco"},
		{"Name": "Mozambique"},
		{"Name": "Myanmar"},
		{"Name": "Namibia"},
		{"Name": "Nauru"},
		{"Name": "Nepal"},
		{"Name": "Netherlands"},
		{"Name": "Netherlands Antilles"},
		{"Name": "New Caledonia"},
		{"Name": "New Zealand"},
		{"Name": "Nicaragua"},
		{"Name": "Niger"},
		{"Name": "Nigeria"},
		{"Name": "Niue"},
		{"Name": "Norfolk Island"},
		{"Name": "Northern Mariana Islands"},
		{"Name": "Norway"},
		{"Name": "Oman"},
		{"Name": "Pakistan"},
		{"Name": "Palau"},
		{"Name": "Palestinian Territory Occupied"},
		{"Name": "Panama"},
		{"Name": "Papua New Guinea"},
		{"Name": "Paraguay"},
		{"Name": "Peru"},
		{"Name": "Philippines"},
		{"Name": "Pitcairn"},
		{"Name": "Poland"},
		{"Name": "Portugal"},
		{"Name": "Puerto Rico"},
		{"Name": "Qatar"},
		{"Name": "Reunion"},
		{"Name": "Romania"},
		{"Name": "Russian Federation"},
		{"Name": "Rwanda"},
		{"Name": "Saint Helena"},
		{"Name": "Saint Kitts Nevis"},
		{"Name": "Saint Lucia"},
		{"Name": "Saint Pierre Miquelon"},
		{"Name": "Saint Vincent Grenadines"},
		{"Name": "Samoa"},
		{"Name": "San Marino"},
		{"Name": "Sao Tome Principe"},
		{"Name": "Saudi Arabia"},
		{"Name": "Senegal"},
		{"Name": "Serbia Montenegro"},
		{"Name": "Seychelles"},
		{"Name": "Sierra Leone"},
		{"Name": "Singapore"},
		{"Name": "Slovakia"},
		{"Name": "Slovenia"},
		{"Name": "Solomon Islands"},
		{"Name": "Somalia"},
		{"Name": "South Africa"},
		{"Name": "South Georgia Islands"},
		{"Name": "Spain"},
		{"Name": "Sri Lanka"},
		{"Name": "Sudan"},
		{"Name": "Suriname"},
		{"Name": "Svalbard Jan Mayen"},
		{"Name": "Swaziland"},
		{"Name": "Sweden"},
		{"Name": "Switzerland"},
		{"Name": "Syrian Arab Republic"},
		{"Name": "Taiwan Province China"},
		{"Name": "Tajikistan"},
		{"Name": "Tanzania United Republic"},
		{"Name": "Thailand"},
		{"Name": "Timor-Leste"},
		{"Name": "Togo"},
		{"Name": "Tokelau"},
		{"Name": "Tonga"},
		{"Name": "Trinidad Tobago"},
		{"Name": "Tunisia"},
		{"Name": "Turkey"},
		{"Name": "Turkmenistan"},
		{"Name": "Turks Caicos Islands"},
		{"Name": "Tuvalu"},
		{"Name": "Uganda"},
		{"Name": "Ukraine"},
		{"Name": "United Arab Emirates"},
		{"Name": "United Kingdom"},
		{"Name": "United States"},
		{"Name": "United Minor Islands"},
		{"Name": "Uruguay"},
		{"Name": "Uzbekistan"},
		{"Name": "Vanuatu"},
		{"Name": "Venezuela"},
		{"Name": "Viet Nam"},
		{"Name": "Virgin Islands British"},
		{"Name": "Virgin Islands"},
		{"Name": "Wallis Futuna"},
		{"Name": "Western Sahara"},
		{"Name": "Yemen"},
		{"Name": "Zambia"},
		{"Name": "Zimbabwe"}
	]
}